jupyterlab_gitlab/__init__.py
jupyterlab_gitlab/_version.py
jupyterlab_gitlab/gitlab.py
jupyterlab_gitlab-4.0.0.data/data/etc/jupyter/jupyter_notebook_config.d/jupyterlab_gitlab.json
jupyterlab_gitlab-4.0.0.data/data/etc/jupyter/jupyter_server_config.d/jupyterlab_gitlab.json
jupyterlab_gitlab-4.0.0.data/data/share/jupyter/labextensions/jupyterlab-gitlab/package.json
jupyterlab_gitlab-4.0.0.data/data/share/jupyter/labextensions/jupyterlab-gitlab/schemas/jupyterlab-gitlab/drive.json
jupyterlab_gitlab-4.0.0.data/data/share/jupyter/labextensions/jupyterlab-gitlab/schemas/jupyterlab-gitlab/package.json.orig
jupyterlab_gitlab-4.0.0.data/data/share/jupyter/labextensions/jupyterlab-gitlab/static/232.2729dbd8de27fb8601e1.js
jupyterlab_gitlab-4.0.0.data/data/share/jupyter/labextensions/jupyterlab-gitlab/static/742.ff0c6cd9a5a3198ebae4.js
jupyterlab_gitlab-4.0.0.data/data/share/jupyter/labextensions/jupyterlab-gitlab/static/747.a85ac71c39deaa0e363e.js
jupyterlab_gitlab-4.0.0.data/data/share/jupyter/labextensions/jupyterlab-gitlab/static/remoteEntry.b1ef8c77a08638c7aec5.js
jupyterlab_gitlab-4.0.0.data/data/share/jupyter/labextensions/jupyterlab-gitlab/static/style.js
jupyterlab_gitlab-4.0.0.data/data/share/jupyter/labextensions/jupyterlab-gitlab/static/third-party-licenses.json
jupyterlab_gitlab-4.0.0.data/data/share/jupyter/labextensions/jupyterlab-gitlab/install.json
jupyterlab_gitlab-4.0.0.dist-info/METADATA
jupyterlab_gitlab-4.0.0.dist-info/WHEEL
jupyterlab_gitlab-4.0.0.dist-info/licenses/LICENSE
jupyterlab_gitlab-4.0.0.dist-info/RECORD
