Metadata-Version: 2.1
Name: jupyterlab_gitlab
Version: 4.0.0
Summary: JupyterLab viewer for GitLab repositories
Project-URL: Homepage, https://gitlab.com/beenje/jupyterlab-gitlab
Project-URL: Bug Tracker, https://gitlab.com/beenje/jupyterlab-gitlab/issues
Project-URL: Repository, https://gitlab.com/beenje/jupyterlab-gitlab
Author-email: Benjamin Bertrand <beenje@gmail.com>
License: BSD 3-Clause License
License-File: LICENSE
Classifier: Framework :: Jupyter
Classifier: Framework :: Jupyter :: JupyterLab
Classifier: Framework :: Jupyter :: JupyterLab :: 4
Classifier: Framework :: Jupyter :: JupyterLab :: Extensions
Classifier: Framework :: Jupyter :: JupyterLab :: Extensions :: Prebuilt
Classifier: License :: OSI Approved :: BSD License
Classifier: Programming Language :: Python
Classifier: Programming Language :: Python :: 3
Classifier: Programming Language :: Python :: 3.8
Classifier: Programming Language :: Python :: 3.9
Classifier: Programming Language :: Python :: 3.10
Classifier: Programming Language :: Python :: 3.11
Requires-Python: >=3.8
Requires-Dist: jupyter-server<3,>=2.0.1
